Petroineos/__init__.py
Petroineos/test.py
Petroineos-1.0.dist-info/METADATA
Petroineos-1.0.dist-info/WHEEL
Petroineos-1.0.dist-info/top_level.txt
Petroineos-1.0.dist-info/RECORD
